text_tagging_model/__init__.py
text_tagging_model/logger_config.py
text_tagging_model/models/__init__.py
text_tagging_model/models/bart_based_model/__init__.py
text_tagging_model/models/bart_based_model/tag_sum_extractor.py
text_tagging_model/models/base_extractor.py
text_tagging_model/models/metrics.py
text_tagging_model/models/rake_based_model/__init__.py
text_tagging_model/models/rake_based_model/keyphrases_extractor.py
text_tagging_model/models/rake_based_model/tags_extractor.py
text_tagging_model/processing/__init__.py
text_tagging_model/processing/embedder/__init__.py
text_tagging_model/processing/embedder/base_embedder.py
text_tagging_model/processing/embedder/fasttext_embedder.py
text_tagging_model/processing/embedder/hg_embedder.py
text_tagging_model/processing/normalizers/__init__.py
text_tagging_model/processing/normalizers/base_normalizer.py
text_tagging_model/processing/normalizers/nouns_keeper.py
text_tagging_model/processing/normalizers/pipe.py
text_tagging_model/processing/normalizers/punctuation_deleter.py
text_tagging_model/processing/normalizers/stopwords_deleter.py
text_tagging_model/processing/ranker/__init__.py
text_tagging_model/processing/ranker/base_ranker.py
text_tagging_model/processing/ranker/max_distance_ranker.py
text_tagging_model/processing/ranker/text_sim_ranker.py
text_tagging_model/processing/summarizator/__init__.py
text_tagging_model/processing/summarizator/bart_summarization.py
text_tagging_model/processing/utils.py
text_tagging_model-0.1.4.dist-info/METADATA
text_tagging_model-0.1.4.dist-info/WHEEL
text_tagging_model-0.1.4.dist-info/RECORD
